stashlib/__init__.py
stashlib/common.py
stashlib/database.py
stashlib/html.py
stashlib/log.py
stashlib/logger.py
stashlib/scene_filename_parser.py
stashlib/sqlite_wrapper.py
stashlib/stash_database.py
stashlib/stash_database_base.py
stashlib/stash_interface.py
stashlib/stash_models.py
stashlib/stash_tables.py
stashlib/table.py
pystashlib-0.6.0.dist-info/METADATA
pystashlib-0.6.0.dist-info/WHEEL
pystashlib-0.6.0.dist-info/top_level.txt
pystashlib-0.6.0.dist-info/RECORD
