Metadata-Version: 2.4
Name: pystashlib
Version: 0.6.0
Summary: A python library for manipulating a stash database
Home-page: https://github.com/7dJx1qP/pystashlib
Author: 7dJx1qP
Author-email: 38586902+7dJx1qP@users.noreply.github.com
License: MIT
Classifier: License :: OSI Approved :: MIT License
Classifier: Programming Language :: Python :: 3
Classifier: Programming Language :: Python :: 3.11
Requires-Dist: cloudscraper
Requires-Dist: pyyaml
Requires-Dist: python-dateutil
Requires-Dist: requests
Provides-Extra: html
Requires-Dist: lxml; extra == "html"
Dynamic: author
Dynamic: author-email
Dynamic: classifier
Dynamic: description
Dynamic: description-content-type
Dynamic: home-page
Dynamic: license
Dynamic: provides-extra
Dynamic: requires-dist
Dynamic: summary
